<?xml version="1.0" encoding="utf-8" ?>
<dwsync>
<file name="search_black_icon.png" server="120.79.9.162//home/wwwroot/dongxisheji/" local="131592907759289430" remote="131622916270000000" Dst="0" />
<file name="search_icon.png" server="120.79.9.162//home/wwwroot/dongxisheji/" local="131592558060000000" remote="131622916280000000" Dst="0" />
<file name="menu_icon.png" server="120.79.9.162//home/wwwroot/dongxisheji/" local="131592558060000000" remote="131622916280000000" Dst="0" />
<file name="view_icon.png" server="120.79.9.162//home/wwwroot/dongxisheji/" local="131598032529223167" remote="131622916280000000" Dst="0" />
<file name="good_icon.png" server="120.79.9.162//home/wwwroot/dongxisheji/" local="131598033065061474" remote="131622916280000000" Dst="0" />
<file name="default-thumbnail.png" server="120.79.9.162//home/wwwroot/dongxisheji/" local="131601023230000000" remote="131601023230000000" Dst="0" />
<file name="default_tupian1.png" server="120.79.9.162//home/wwwroot/dongxisheji/" local="131601023230000000" remote="131601023230000000" Dst="0" />
<file name="news_datail.png" server="120.79.9.162//home/wwwroot/dongxisheji/" local="131601023240000000" remote="131601023240000000" Dst="0" />
<file name="news_img.png" server="120.79.9.162//home/wwwroot/dongxisheji/" local="131601023250000000" remote="131601023250000000" Dst="0" />
<file name="headicon_128.png" server="120.79.9.162//home/wwwroot/dongxisheji/" local="131601023230000000" remote="131601023230000000" Dst="0" />
<file name="works_img.png" server="120.79.9.162//home/wwwroot/dongxisheji/" local="131601023250000000" remote="131601023250000000" Dst="0" />
<file name="qq_icon.png" server="120.79.9.162//home/wwwroot/dongxisheji/" local="131601023250000000" remote="131601023250000000" Dst="0" />
<file name="wechat_icon.png" server="120.79.9.162//home/wwwroot/dongxisheji/" local="131601023250000000" remote="131601023250000000" Dst="0" />
<file name="erweima.png" server="120.79.9.162//home/wwwroot/dongxisheji/" local="131601023230000000" remote="131601023230000000" Dst="0" />
<file name="headicon_50.png" server="120.79.9.162//home/wwwroot/dongxisheji/" local="131601023240000000" remote="131601023240000000" Dst="0" />
<file name="banner.png" server="120.79.9.162//home/wwwroot/dongxisheji/" local="131601023230000000" remote="131601023230000000" Dst="0" />
<file name="newimg.png" server="120.79.9.162//home/wwwroot/dongxisheji/" local="131601023240000000" remote="131601023240000000" Dst="0" />
<file name="server.png" server="120.79.9.162//home/wwwroot/dongxisheji/" local="131601023250000000" remote="131601023250000000" Dst="0" />
<file name="default_tupian4.png" server="120.79.9.162//home/wwwroot/dongxisheji/" local="131601023230000000" remote="131601023230000000" Dst="0" />
<file name="main1.png" server="120.79.9.162//home/wwwroot/dongxisheji/" local="131601023240000000" remote="131601023240000000" Dst="0" />
<file name="main2.png" server="120.79.9.162//home/wwwroot/dongxisheji/" local="131601023240000000" remote="131601023240000000" Dst="0" />
<file name="main3.png" server="120.79.9.162//home/wwwroot/dongxisheji/" local="131601023240000000" remote="131601023240000000" Dst="0" />
<file name="favicon.ico" server="120.79.9.162//home/wwwroot/dongxisheji/" local="131601023230000000" remote="131601023230000000" Dst="0" />
<file name="headicon_40.png" server="120.79.9.162//home/wwwroot/dongxisheji/" local="131601023240000000" remote="131601023240000000" Dst="0" />
<file name="logo.png" server="120.79.9.162//home/wwwroot/dongxisheji/" local="131601023240000000" remote="131601023240000000" Dst="0" />
<file name="headicon.png" server="120.79.9.162//home/wwwroot/dongxisheji/" local="131601023230000000" remote="131601023230000000" Dst="0" />
<file name="main4.png" server="120.79.9.162//home/wwwroot/dongxisheji/" local="131601023240000000" remote="131601023240000000" Dst="0" />
<file name="headicon_30.png" server="120.79.9.162//home/wwwroot/dongxisheji/" local="131601023230000000" remote="131601023230000000" Dst="0" />
<file name="init.jpg" server="120.79.9.162//home/wwwroot/dongxisheji/" local="131622754860000000" remote="131622916390000000" Dst="0" />
</dwsync>